airflow/providers/qlik_sense/__init__.py
airflow/providers/qlik_sense/hooks/__init__.py
airflow/providers/qlik_sense/hooks/qlik_sense_hook.py
airflow/providers/qlik_sense/hooks/qlik_sense_hook_cert.py
airflow/providers/qlik_sense/hooks/qlik_sense_hook_jwt.py
airflow/providers/qlik_sense/hooks/qlik_sense_hook_ntlm.py
airflow/providers/qlik_sense/operators/__init__.py
airflow/providers/qlik_sense/operators/reload_app_operator.py
airflow/providers/qlik_sense/operators/reload_externaltask_operator.py
airflow/providers/qlik_sense/operators/reload_task_operator.py
airflow_provider_qlik_sense_client_managed-0.0.5.dist-info/licenses/LICENSE
airflow_provider_qlik_sense_client_managed-0.0.5.dist-info/METADATA
airflow_provider_qlik_sense_client_managed-0.0.5.dist-info/WHEEL
airflow_provider_qlik_sense_client_managed-0.0.5.dist-info/entry_points.txt
airflow_provider_qlik_sense_client_managed-0.0.5.dist-info/top_level.txt
airflow_provider_qlik_sense_client_managed-0.0.5.dist-info/RECORD
