Metadata-Version: 2.4
Name: airflow-provider-qlik-sense-client-managed
Version: 0.0.5
Summary: Airflow package provider to perform action into Qlik Sense On-Promise (reload apps, tasks ...).
Home-page: 
Author: Clement Parsy
Author-email: cparsy@decideom.fr
License: Apache License 2.0
Classifier: Framework :: Apache Airflow
Classifier: Framework :: Apache Airflow :: Provider
Requires-Python: ~=3.9
License-File: LICENSE
Requires-Dist: apache-airflow>=2.10
Requires-Dist: requests-ntlm2>=6.5.3
Dynamic: author
Dynamic: author-email
Dynamic: classifier
Dynamic: description
Dynamic: description-content-type
Dynamic: license
Dynamic: license-file
Dynamic: requires-dist
Dynamic: requires-python
Dynamic: summary
